Workbook

Sheet Artikel
A1: Snackautomat: Artikelvergleich (pro Stück und pro Monat)
A2: Blau = Eingabe/Annahme (änderbar). Schwarz = Formel. Gelb = wichtigste Annahmen, bitte mit echten Angeboten ersetzen.
A3: Globale Annahmen:
A4: Kartenzahlungs-/Abrechnungsgebühr (% vom Brutto) | D4: 0.05 | E4: Annahme: Nayax o. ä. Abrechnungsgebühren plus Barzahlungsanteil gemittelt; Angebot einholen.
A5: Standortprovision an Vermieter (% vom Brutto) | D5: 0.15 | E5: Annahme: üblich ist Umsatzbeteiligung oder feste Miete (MTR Legal, Automatenaufstellvertrag). Satz verhandelbar.
A6: Verkaufstage pro Monat | D6: 30
A7: Absatzfaktor Szenario (0,6 = vorsichtig, 1 = Basis, 1,5 = guter Standort) | D7: 1 | E7: Ein Betreiber berichtet 80 bis 150 € Umsatz pro Tag als Norm (getquin). Basis hier bewusst niedriger.
A9: Artikel | B9: Typ | C9: Bezugsquelle | D9: EK netto / Stück | E9: VK brutto / Stück | F9: MwSt | G9: VK netto | H9: Gebühr + Provision | I9: Deckungsbeitrag / Stück | J9: Marge (% vom Netto-VK) | K9: Verkäufe / Tag (Annahme) | L9: DB / Monat | M9: Rang (DB/Monat) | N9: Zielgruppe | O9: Herkunft der Zahlen
A10: Red Bull 250 ml | B10: Wiederverkauf | C10: Metro / Getränkegroßhandel | D10: 1.13 | E10: 2.8 | F10: 0.19 | G10: =E10/(1+F10) -> 2.3529412 | H10: =E10*($D$4+$D$5) -> 0.56 | I10: =G10-D10-H10 -> 0.66294118 | J10: =IF(G10=0,0,I10/G10) -> 0.28175 | K10: 6 | L10: =I10*K10*$D$6*$D$7 -> 119.32941 | M10: =RANK(L10,$L$10:$L$19) -> 3 | N10: Alle, v. a. Studis, Schicht | O10: EK: Metro-Prospekt ab 4,52 € (vermutlich 4er-Pack, also ca. 1,13 €/Dose), Pfand durchlaufend. VK: Annahme.
A11: Wasser 0,5 l | B11: Wiederverkauf | C11: Getränkegroßhandel | D11: 0.3 | E11: 1.5 | F11: 0.19 | G11: =E11/(1+F11) -> 1.2605042 | H11: =E11*($D$4+$D$5) -> 0.3 | I11: =G11-D11-H11 -> 0.6605042 | J11: =IF(G11=0,0,I11/G11) -> 0.524 | K11: 8 | L11: =I11*K11*$D$6*$D$7 -> 158.52101 | M11: =RANK(L11,$L$10:$L$19) -> 1 | N11: Alle | O11: Annahme. Wasser ist laut VMFS der meistverkaufte Automatenartikel.
A12: Proteinriegel (Barebells) | B12: Wiederverkauf | C12: Großhandel / Barebells B2B | D12: 1.6 | E12: 3 | F12: 0.07 | G12: =E12/(1+F12) -> 2.8037383 | H12: =E12*($D$4+$D$5) -> 0.6 | I12: =G12-D12-H12 -> 0.60373832 | J12: =IF(G12=0,0,I12/G12) -> 0.21533333 | K12: 4 | L12: =I12*K12*$D$6*$D$7 -> 72.448598 | M12: =RANK(L12,$L$10:$L$19) -> 6 | N12: Gym, Büro, Studis | O12: EK-Annahme. Referenz: 12er ab 21 € brutto im Amazon-Abo (1,75 €/Stück). VK: Annahme.
A13: Xylit-Kaugummi 10er (Extra Professional) | B13: Wiederverkauf | C13: Großhandel / Metro | D13: 0.7 | E13: 1.5 | F13: 0.07 | G13: =E13/(1+F13) -> 1.4018692 | H13: =E13*($D$4+$D$5) -> 0.3 | I13: =G13-D13-H13 -> 0.40186916 | J13: =IF(G13=0,0,I13/G13) -> 0.28666667 | K13: 3 | L13: =I13*K13*$D$6*$D$7 -> 36.168224 | M13: =RANK(L13,$L$10:$L$19) -> 10 | N13: Mensa, Büro, Kantine | O13: EK-Referenz: 30 x 10er für 22,90 € brutto (eBay, 0,76 €/Pack). VK: Annahme.
A14: Koffein-Gum Markenware (z. B. enerjetix, Guming) | B14: Wiederverkauf | C14: Hersteller direkt anfragen | D14: 2 | E14: 3.5 | F14: 0.07 | G14: =E14/(1+F14) -> 3.271028 | H14: =E14*($D$4+$D$5) -> 0.7 | I14: =G14-D14-H14 -> 0.57102804 | J14: =IF(G14=0,0,I14/G14) -> 0.17457143 | K14: 3 | L14: =I14*K14*$D$6*$D$7 -> 51.392523 | M14: =RANK(L14,$L$10:$L$19) -> 8 | N14: Uni-Bib, Nachtschicht, Coworking | O14: EK-Annahme, keine öffentlichen B2B-Preise gefunden. Hersteller anfragen.
A15: Koffein-Gum Eigenmarke (100 % Xylit, 10er) | B15: Eigenmarke | C15: Private Label: Accio/China oder EU-Hersteller (Wonnda) | D15: 0.9 | E15: 3 | F15: 0.07 | G15: =E15/(1+F15) -> 2.8037383 | H15: =E15*($D$4+$D$5) -> 0.6 | I15: =G15-D15-H15 -> 1.3037383 | J15: =IF(G15=0,0,I15/G15) -> 0.465 | K15: 3 | L15: =I15*K15*$D$6*$D$7 -> 117.33645 | M15: =RANK(L15,$L$10:$L$19) -> 4 | N15: Uni-Bib, Nachtschicht, Coworking | O15: EK-Annahme inkl. Fracht/Zoll. Mehrere OEM-Anbieter auf Accio, MOQ meist 500+. Muster anfragen.
A16: Energy Pouches Markenware (z. B. BAGZ Energy 5er) | B16: Wiederverkauf | C16: Großhändler/Distributor anfragen | D16: 1.8 | E16: 3.5 | F16: 0.07 | G16: =E16/(1+F16) -> 3.271028 | H16: =E16*($D$4+$D$5) -> 0.7 | I16: =G16-D16-H16 -> 0.77102804 | J16: =IF(G16=0,0,I16/G16) -> 0.23571429 | K16: 2 | L16: =I16*K16*$D$6*$D$7 -> 46.261682 | M16: =RANK(L16,$L$10:$L$19) -> 9 | N16: Coworking, Gym, Studis 18+ | O16: Endkundenpreis BAGZ Energy 5er: 2,95 € (tabakdealer.de). EK-Annahme. MwSt-Satz prüfen.
A17: Energy Pouches Eigenmarke (Dose) | B17: Eigenmarke | C17: Private Label über Wonnda (Europouches, Kylmakorpi, hiit) | D17: 1.2 | E17: 4.5 | F17: 0.07 | G17: =E17/(1+F17) -> 4.2056075 | H17: =E17*($D$4+$D$5) -> 0.9 | I17: =G17-D17-H17 -> 2.1056075 | J17: =IF(G17=0,0,I17/G17) -> 0.50066667 | K17: 2 | L17: =I17*K17*$D$6*$D$7 -> 126.33645 | M17: =RANK(L17,$L$10:$L$19) -> 2 | N17: Coworking, Gym, Studis 18+ | O17: EK-Annahme. Hersteller auf Wonnda gelistet, Angebot einholen. Rechtlicher Graubereich beachten.
A18: Elektrolyt-Sticks Eigenmarke (3er) | B18: Eigenmarke | C18: Private Label (Accio, ab ca. 0,10 $/Einheit) | D18: 0.45 | E18: 2.5 | F18: 0.07 | G18: =E18/(1+F18) -> 2.3364486 | H18: =E18*($D$4+$D$5) -> 0.5 | I18: =G18-D18-H18 -> 1.3864486 | J18: =IF(G18=0,0,I18/G18) -> 0.5934 | K18: 2 | L18: =I18*K18*$D$6*$D$7 -> 83.186916 | M18: =RANK(L18,$L$10:$L$19) -> 5 | N18: Gym, Sportplatz | O18: EK-Annahme (ca. 0,15 €/Stick). Referenz Endkunde: sanotact 50 Sticks 8,95 € bei dm.
A19: Hard Gum (Kieferlinie-Trend) | B19: Eigenmarke | C19: Private Label (Accio: Jawline Gum OEM) | D19: 1 | E19: 3 | F19: 0.07 | G19: =E19/(1+F19) -> 2.8037383 | H19: =E19*($D$4+$D$5) -> 0.6 | I19: =G19-D19-H19 -> 1.2037383 | J19: =IF(G19=0,0,I19/G19) -> 0.42933333 | K19: 2 | L19: =I19*K19*$D$6*$D$7 -> 72.224299 | M19: =RANK(L19,$L$10:$L$19) -> 7 | N19: Gym, Gen-Z-Jungs | O19: EK- und VK-Annahme. OEM-Angebote auf Accio vorhanden.
A21: Hinweis MwSt: Lebensmittel inkl. Kaugummi/NEM i. d. R. 7 %, Getränke 19 %. Mit Steuerberater prüfen. Bei Kleinunternehmerregelung entfällt die MwSt.
A22: Hinweis Koffein: In DE nicht altersbeschränkt, aber Koffein-Gum und Pouches nur an Erwachsenen-Standorten anbieten (Uni, Büro, Gym), nicht an Schulen.

Sheet Automat
A1: Ein Automat: zwei Sortiments-Mixe im Vergleich
A2: Spalten C und D: 1 = Artikel ist im Mix, 0 = nicht. Absatz und Preise kommen aus dem Blatt 'Artikel'.
A4: Artikel | B4: DB / Monat (aus Artikel) | C4: Mix A: Klassisch | D4: Mix B: Fokus/Funktional
A5: =Artikel!A10 -> Red Bull 250 ml | B5: =Artikel!L10 -> 119.32941 | C5: 1 | D5: 1
A6: =Artikel!A11 -> Wasser 0,5 l | B6: =Artikel!L11 -> 158.52101 | C6: 1 | D6: 1
A7: =Artikel!A12 -> Proteinriegel (Barebells) | B7: =Artikel!L12 -> 72.448598 | C7: 1 | D7: 0
A8: =Artikel!A13 -> Xylit-Kaugummi 10er (Extra Professional) | B8: =Artikel!L13 -> 36.168224 | C8: 1 | D8: 1
A9: =Artikel!A14 -> Koffein-Gum Markenware (z. B. enerjetix, Guming) | B9: =Artikel!L14 -> 51.392523 | C9: 0 | D9: 0
A10: =Artikel!A15 -> Koffein-Gum Eigenmarke (100 % Xylit, 10er) | B10: =Artikel!L15 -> 117.33645 | C10: 0 | D10: 1
A11: =Artikel!A16 -> Energy Pouches Markenware (z. B. BAGZ Energy 5er) | B11: =Artikel!L16 -> 46.261682 | C11: 0 | D11: 0
A12: =Artikel!A17 -> Energy Pouches Eigenmarke (Dose) | B12: =Artikel!L17 -> 126.33645 | C12: 0 | D12: 1
A13: =Artikel!A18 -> Elektrolyt-Sticks Eigenmarke (3er) | B13: =Artikel!L18 -> 83.186916 | C13: 0 | D13: 1
A14: =Artikel!A19 -> Hard Gum (Kieferlinie-Trend) | B14: =Artikel!L19 -> 72.224299 | C14: 0 | D14: 1
A16: Deckungsbeitrag Sortiment / Monat | C16: =SUMPRODUCT($B$5:$B$14,C5:C14) -> 386.46724 | D16: =SUMPRODUCT($B$5:$B$14,D5:D14) -> 713.10276
A18: Laufende Kosten / Monat
A19: Kartenleser/Telemetrie-Grundgebühr | B19: 10 | E19: Annahme. Nayax erhebt eine monatliche Gebühr, Höhe im Angebot erfragen.
A20: Fahrten, Nachfüllen, Zeit (pauschal) | B20: 40 | E20: Annahme: 4 Fahrten im Monat in Berlin.
A21: Strom (falls nicht vom Standort getragen) | B21: 0 | E21: Annahme: Standort stellt Strom, sonst ca. 15 bis 30 € eintragen.
A22: Schwund/Verfall (pauschal) | B22: 10 | E22: Annahme.
A23: Summe laufende Kosten | B23: =SUM(B19:B22) -> 60 | C23: =$B$23 -> 60 | D23: =$B$23 -> 60
A25: Gewinn vor Steuern / Monat | C25: =C16-C23 -> 326.46724 | D25: =D16-D23 -> 653.10276
A27: Einmalige Investition
A28: Snackautomat gebraucht | B28: 2000 | E28: Annahme Marktpreis Kleinanzeigen. Neu ab 4.770 € (DGA Vending).
A29: Kartenleser inkl. Einbau | B29: 400 | E29: Basis: Nayax-Leser ca. 360 $ plus Einbau (Capital Vending), EU-Version 199 bis 349 $.
A30: Erstbefüllung Ware | B30: 300 | E30: Annahme.
A31: Eigenmarke: Mindestmenge erste Charge (nur Mix B) | B31: 1500 | E31: Annahme: MOQ 500 bis 1.000 Einheiten (Wonnda) je Produkt, hier gemittelt.
A32: Investition gesamt | C32: =SUM(B28:B30) -> 2700 | D32: =SUM(B28:B31) -> 4200
A33: Amortisation (Monate) | C33: =IF(C25<=0,"nie",C32/C25) -> 8.270355 | D33: =IF(D25<=0,"nie",D32/D25) -> 6.430841
A35: Umsatz brutto / Tag (Kontrolle) | C35: =SUMPRODUCT(Artikel!$E$10:$E$19,Artikel!$K$10:$K$19,C5:C14)*Artikel!$D$7 -> 45.3 | D35: =SUMPRODUCT(Artikel!$E$10:$E$19,Artikel!$K$10:$K$19,D5:D14)*Artikel!$D$7 -> 62.3 | E35: Zum Abgleich mit Betreibererfahrung von 80 bis 150 € Umsatz pro Tag (getquin).

Sheet Zielgruppen
A1: Standorte, Zielgruppen und wie du sie erreichst
A3: Standort | B3: Zielgruppe | C3: Passende Artikel | D3: Warum es passt | E3: So kommst du rein | F3: Eignung
A4: Uni-Bibliothek / Lernräume / Studentenwohnheim | B4: Studis 18 bis 28, Prüfungsphasen, abends | C4: Koffein-Gum, Xylit-Gum, Wasser, Energy | D4: Lange Lernsessions, kaum Alternativen nachts, Gum ist leise und erlaubt in der Bib | E4: Studierendenwerk/Wohnheimverwaltung anfragen; bei öffentlichen Häusern oft Ausschreibung | F4: Sehr hoch
A5: Coworking / Startup-Büros | B5: Gründer, Devs, Remote Worker 25 bis 40 | C5: Koffein-Gum, Pouches, Proteinriegel, Wasser | D5: Zahlungsbereit, offen für neue Produkte, Content-tauglich | E5: Direkt Community-Manager anschreiben, Umsatzbeteiligung anbieten | F5: Hoch
A6: Gym / Boulderhalle | B6: Sportler 18 bis 35 | C6: Elektrolyte, Hard Gum, Proteinriegel, Wasser | D6: Elektrolyte und Protein werden dort direkt gebraucht | E6: Inhaber direkt ansprechen, oft schon Getränkekühlschrank vorhanden | F6: Hoch
A7: Krankenhaus / Pflege (Nachtschicht) | B7: Pflegekräfte, Ärzte | C7: Koffein-Gum, Xylit-Gum, Wasser | D7: Nachtschichten, wenig Zeit für Kaffee | E7: Meist Ausschreibung und Gebühr (laut WeYou-Interview), schwerer Einstieg | F7: Mittel
A8: Bahnhof / öffentliche Plätze | B8: Gemischt, inkl. Minderjährige | C8: Wasser, Energy, Xylit-Gum | D8: Hohe Frequenz | E8: Teure Flächen, starke Konkurrenz; Koffeinprodukte hier eher meiden | F8: Niedrig

Sheet Quellen
A1: Quellen und Annahmen
A3: Was | B3: Link
A4: Metro Red Bull Preis ab 4,52 € (KW 31/2026) | B4: https://www.kaufda.de/Metro/Sortiment/Red-Bull
A5: Barebells 12er ab 21 € im Amazon-Abo | B5: https://www.mein-deal.com/?p=2164912
A6: Extra Professional 30 x 10er für 22,90 € | B6: https://www.ebay.de/p/28014800363
A7: BAGZ Energy Koffeinbeutel 2,95 € (5 Stück) | B7: https://tabakdealer.de/bagz/kautabak/
A8: sanotact Elektrolyte 50 Sticks 8,95 € | B8: https://www.dm.de/p/d/3085316/
A9: Koffein-Gum Private Label Anbieter (Accio) | B9: https://de.accio.com/plp/caffeine-gum-white-label
A10: Energy-Pouch Private-Label-Hersteller (Wonnda) | B10: https://wonnda.com/de/produkttypen/private-label-energy-pouches-hersteller/
A11: White-Label-MOQ 500 bis 5.000 Einheiten (Wonnda) | B11: https://wonnda.com/de/magazin/white-label-nahrungsergaenzungsmittel-hersteller-europa/
A12: Snackautomat neu ab 4.770 € (DGA Vending) | B12: https://www.kleinanzeigen.de/pro/dga-vending
A13: Nayax-Kartenleser ca. 360 $ plus Einbau | B13: https://dev.capitalvending.com/nayax-reader-with-installation-at-capital-vending
A14: Betreiber-Erfahrung 80 bis 150 € Umsatz/Tag | B14: https://app.getquin.com/de/post/kJiXqaBssQ/hier-mal-ein-kleines-update-zu-meinen-erfahrung-im-automaten-business
... A17: Öffentliche Standorte: Ausschreibung und Gebühr (WeYou) | B17: https://www.stol.it/artikel/wirtschaft/hinter-den-kulissen-des-kaffeegenusses-die-welt-der-verkaufsautomaten
A19: Alles, was in Blatt 'Artikel' mit 'Annahme' markiert ist, ist geschätzt und sollte durch echte Angebote ersetzt werden.
